python_ddd
